understory/apps/text_editor/__init__.py
understory/apps/text_editor/templates/__init__.py
understory/apps/text_editor/templates/editor.html
understory_text_editor-0.0.6.dist-info/entry_points.txt
understory_text_editor-0.0.6.dist-info/LICENSE
understory_text_editor-0.0.6.dist-info/WHEEL
understory_text_editor-0.0.6.dist-info/METADATA
understory_text_editor-0.0.6.dist-info/RECORD
