Metadata-Version: 2.1
Name: understory-text-editor
Version: 0.0.6
Summary: A text editor for the Understory framework.
License: CC0-1.0
Author: Angelo Gladding
Author-email: self@angelogladding.com
Requires-Python: >=3.9,<4.0
Classifier: License :: CC0 1.0 Universal (CC0 1.0) Public Domain Dedication
Classifier: Programming Language :: Python :: 3
Classifier: Programming Language :: Python :: 3.9
Requires-Dist: micropub (>=0,<1)
Requires-Dist: understory (>=0,<1)
